{"description":"La Direction Générale des Finances Publiques","name":"DGFIP","pages":[{"sitename":"DGFIP","siteslug":"dgfip","slug":"amendes"},{"sitename":"DGFIP","siteslug":"dgfip","slug":"prelevement-a-la-source"},{"sitename":"DGFIP","siteslug":"dgfip","slug":"timbres"}],"websites":{"amendes":{"audits":{"accessibility":{"rgaa":[{"context":null,"date":"2022-03-25","score":{"compliance":71,"complianceaverage":88,"criteria":{"conforme":45,"nonapplicable":43,"nonconforme":18,"nonteste":0,"total":106}},"url":"audits/amendes/accessibility/2022-03-25.csv"},{"context":null,"date":"2022-03-15","score":{"compliance":74,"complianceaverage":89,"criteria":{"conforme":47,"nonapplicable":43,"nonconforme":16,"nonteste":0,"total":106}},"url":"audits/amendes/accessibility/2022-03-15.csv"},{"context":{"audit":{"condition":"Auto-évaluation","environment":["MacOS","Firefox","Chrome","VoiceOver"],"guidelines":"RGAA 4.1","technologies":["HTML","CSS","JS","PDF"],"tools":["Wave","AXE","Web Developper","Usability Hike","Heading Maps"]},"contacts":{"address":"139 rue de Bercy, 75572 Paris, Cedex 12","email":"stap-amendes@dgfip.finances.gouv.fr"},"declared":true,"path":"content/audits/amendes/accessibility/","website":"amendes.gouv.fr"},"date":"2021-03-05","score":{"compliance":58,"complianceaverage":74,"criteria":{"conforme":37,"nonapplicable":43,"nonconforme":26,"nonteste":0,"total":106}},"url":"audits/amendes/accessibility/2021-03-05.csv"},{"context":{"audit":{"condition":"Auto-évaluation","environment":["MacOS","Firefox","Chrome","VoiceOver"],"guidelines":"RGAA 4.0","technologies":["HTML","CSS","JS","PDF"],"tools":["Wave","AXE","Web Developper","Usability Hike","Heading Maps"]},"contacts":{"address":"139 rue de Bercy, 75572 Paris, Cedex 12","email":"stap-amendes@dgfip.finances.gouv.fr"},"declared":true,"path":"content/audits/amendes/accessibility/","website":"amendes.gouv.fr"},"date":"2020-10-12","score":{"compliance":29,"complianceaverage":49,"criteria":{"conforme":17,"nonapplicable":41,"nonconforme":40,"nonteste":0,"total":98}},"url":"audits/amendes/accessibility/2020-10-12.csv"}],"urls":{"api":"audits/amendes/accessibility.json","declaration":"audits/amendes/declaration.txt"}},"performance":{"scores":{"0":{"indexes":{"LCP":9125,"co2":1.6874636178045046,"domsize":539,"eau":2.531195426706757,"ecoindex":"C","ecoindexclass":"medium","ecoscore":65.62681910977477,"pageweight":1675428,"requests":30,"speedindex":"G","speedindexclass":"verybad","speedscore":0.52},"url":"audits/amendes/lighthouse/2020-10-15.json"},"1":{"indexes":{"LCP":7884,"co2":1.4134903131123286,"domsize":140,"eau":2.120235469668493,"ecoindex":"A","ecoindexclass":"good","ecoscore":79.32548434438357,"pageweight":1008324,"requests":18,"speedindex":"G","speedindexclass":"verybad","speedscore":0.43},"url":"audits/amendes/lighthouse/2021-05-17.json"}},"urls":{"api":"audits/amendes/performance.json"}},"recommendation":{"scores":{"0":{"indexes":{"checked":48,"critical":26,"date":"2020-10-12","important":27,"medium":29,"pathlen":2,"total":87,"type":{"code":31,"structure":7,"text":18,"visual":31}},"url":"audits/amendes/quality/2020-10-12.yml"},"1":{"indexes":{"checked":34,"critical":5,"date":"2021-03-05","important":14,"medium":42,"pathlen":2,"total":77,"type":{"code":36,"structure":2,"text":16,"visual":18}},"url":"audits/amendes/quality/2021-03-05.yml"}},"urls":{"api":"audits/amendes/recommendation.json"}}},"slug":"amendes","title":"Paiement des amendes"},"prelevement-a-la-source":{"audits":{"accessibility":{"rgaa":[{"context":{"audit":{"environment":["MacOS","Chrome","VoiceOver"],"guidelines":"RGAA 4.0","technologies":["HTML","CSS"],"tools":["Wave","AXE","MOZ DevTools","Usability Hike"]},"contacts":null,"declared":{"audit":{"environment":["MacOS","Chrome","VoiceOver"],"guidelines":"RGAA 4.0","technologies":["HTML","CSS"],"tools":["Wave","AXE","MOZ DevTools","Usability Hike"]}},"path":"/audits/prelevement-a-la-source/accessibility.md","website":null},"date":"2020-10-22","score":{"compliance":30,"complianceaverage":57,"criteria":{"conforme":13,"nonapplicable":23,"nonconforme":30,"nonteste":0,"total":66}},"url":"audits/prelevement-a-la-source/accessibility/2020-10-22.csv"}],"urls":{"api":"audits/prelevement-a-la-source/accessibility.json","declaration":"audits/prelevement-a-la-source/declaration.txt"}}},"slug":"prelevement-a-la-source","title":"Prélèvement à la source"},"timbres":{"audits":{"accessibility":{"rgaa":[{"context":{"audit":{"environment":["MacOS","Chrome","VoiceOver"],"guidelines":"RGAA 4.0","technologies":["HTML","CSS"],"tools":["Wave","AXE","MOZ DevTools","Usability Hike"]},"contacts":null,"declared":{"audit":{"environment":["MacOS","Chrome","VoiceOver"],"guidelines":"RGAA 4.0","technologies":["HTML","CSS"],"tools":["Wave","AXE","MOZ DevTools","Usability Hike"]}},"path":"/audits/timbres/accessibility.md","website":null},"date":"2020-01-15","score":{"compliance":60,"complianceaverage":69,"criteria":{"conforme":9,"nonapplicable":8,"nonconforme":6,"nonteste":0,"total":23}},"url":"audits/timbres/accessibility/2020-01-15.csv"}],"urls":{"api":"audits/timbres/accessibility.json","declaration":"audits/timbres/declaration.txt"}},"performance":{"scores":{"0":{"indexes":{"LCP":4330,"co2":1.137430822586047,"domsize":105,"eau":1.7061462338790707,"ecoindex":"A","ecoindexclass":"good","ecoscore":93.12845887069764,"pageweight":335015,"requests":18,"speedindex":"G","speedindexclass":"verybad","speedscore":0.39},"url":"audits/timbres/lighthouse/2021-01-29.json"}},"urls":{"api":"audits/timbres/performance.json"}}},"slug":"timbres","title":"Achat de timbres fiscaux électroniques"}}}