{"description":"La direction générale des douanes et droits indirects","name":"Douanes","pages":[{"sitename":"Douanes","siteslug":"douanes","slug":"bordereaux-vente-detaxe"},{"sitename":"Douanes","siteslug":"douanes","slug":"consultation-tarif-douanier"},{"sitename":"Douanes","siteslug":"douanes","slug":"contributions-indirectes-en-ligne"},{"sitename":"Douanes","siteslug":"douanes","slug":"declaration-douane-fret"},{"sitename":"Douanes","siteslug":"douanes","slug":"declaration-echanges-de-biens"},{"sitename":"Douanes","siteslug":"douanes","slug":"declaration-europeenne-service"},{"sitename":"Douanes","siteslug":"douanes","slug":"declaration-transit"},{"sitename":"Douanes","siteslug":"douanes","slug":"gestion-mouvements-marchandises"},{"sitename":"Douanes","siteslug":"douanes","slug":"portail-douane"},{"sitename":"Douanes","siteslug":"douanes","slug":"procedure-communautaire"}],"websites":{"bordereaux-vente-detaxe":{"audits":{"accessibility":{"rgaa":[{"context":{"audit":{"environment":["MacOS","Chrome","VoiceOver"],"guidelines":"RGAA 4.1","technologies":["HTML","CSS"],"tools":["Wave","AXE","MOZ DevTools","Usability Hike"]},"contacts":{"address":"11, rue des deux Communes, 93558 Montreuil, cedex FRANCE","email":"referent-accessibilite@douane.finances.gouv.fr"},"declared":{"audit":{"environment":["MacOS","Chrome","VoiceOver"],"guidelines":"RGAA 4.1","technologies":["HTML","CSS"],"tools":["Wave","AXE","MOZ DevTools","Usability Hike"]}},"path":"/audits/bordereaux-vente-detaxe/index.md","website":null},"date":"2021-10-22","score":{"compliance":69,"complianceaverage":74,"criteria":{"conforme":38,"nonapplicable":51,"nonconforme":17,"nonteste":0,"total":106}},"url":"audits/bordereaux-vente-detaxe/accessibility/2021-10-22.csv"},{"context":null,"date":"2021-03-15","score":{"compliance":56,"complianceaverage":65,"criteria":{"conforme":17,"nonapplicable":46,"nonconforme":13,"nonteste":0,"total":76}},"url":"audits/bordereaux-vente-detaxe/accessibility/2021-03-15.csv"}],"urls":{"api":"audits/bordereaux-vente-detaxe/accessibility.json","declaration":"audits/bordereaux-vente-detaxe/declaration.txt"}}},"slug":"bordereaux-vente-detaxe","title":"Détaxe électronique pour les touristes (PABLO-I)"},"consultation-tarif-douanier":{"audits":{"accessibility":{"rgaa":[{"context":{"audit":{"environment":["MacOS","Chrome","VoiceOver"],"guidelines":"RGAA 4.1","technologies":["HTML","CSS"],"tools":["Wave","AXE","MOZ DevTools","Usability Hike"]},"contacts":{"address":"11, rue des deux Communes, 93558 Montreuil, cedex FRANCE","email":"referent-accessibilite@douane.finances.gouv.fr"},"declared":{"audit":{"environment":["MacOS","Chrome","VoiceOver"],"guidelines":"RGAA 4.1","technologies":["HTML","CSS"],"tools":["Wave","AXE","MOZ DevTools","Usability Hike"]}},"path":"/audits/consultation-tarif-douanier/index.md","website":null},"date":"2021-03-15","score":{"compliance":37,"complianceaverage":41,"criteria":{"conforme":18,"nonapplicable":57,"nonconforme":30,"nonteste":0,"total":105}},"url":"audits/consultation-tarif-douanier/accessibility/2021-03-15.csv"}],"urls":{"api":"audits/consultation-tarif-douanier/accessibility.json","declaration":"audits/consultation-tarif-douanier/declaration.txt"}}},"slug":"consultation-tarif-douanier","title":"Tarif douanier communautaire et national (RITA)"},"contributions-indirectes-en-ligne":{"audits":{"accessibility":{"rgaa":[{"context":{"audit":{"environment":["MacOS","Chrome","VoiceOver"],"guidelines":"RGAA 4.1","technologies":["HTML","CSS"],"tools":["Wave","AXE","MOZ DevTools","Usability Hike"]},"contacts":{"address":"11, rue des deux Communes, 93558 Montreuil, cedex FRANCE","email":"referent-accessibilite@douane.finances.gouv.fr"},"declared":{"audit":{"environment":["MacOS","Chrome","VoiceOver"],"guidelines":"RGAA 4.1","technologies":["HTML","CSS"],"tools":["Wave","AXE","MOZ DevTools","Usability Hike"]}},"path":"/audits/contributions-indirectes-en-ligne/index.md","website":null},"date":"2022-05-19","score":{"compliance":70,"complianceaverage":75,"criteria":{"conforme":35,"nonapplicable":56,"nonconforme":15,"nonteste":0,"total":106}},"url":"audits/contributions-indirectes-en-ligne/accessibility/2022-05-19.csv"},{"context":null,"date":"2022-04-05","score":{"compliance":44,"complianceaverage":64,"criteria":{"conforme":22,"nonapplicable":56,"nonconforme":28,"nonteste":0,"total":106}},"url":"audits/contributions-indirectes-en-ligne/accessibility/2022-04-05.csv"},{"context":null,"date":"2021-03-15","score":{"compliance":44,"complianceaverage":66,"criteria":{"conforme":22,"nonapplicable":57,"nonconforme":27,"nonteste":0,"total":106}},"url":"audits/contributions-indirectes-en-ligne/accessibility/2021-03-15.csv"}],"urls":{"api":"audits/contributions-indirectes-en-ligne/accessibility.json","declaration":"audits/contributions-indirectes-en-ligne/declaration.txt"}},"performance":{"scores":{"0":{"indexes":{"LCP":5676,"co2":1.2302556387278538,"domsize":42,"eau":1.8453834580917805,"ecoindex":"A","ecoindexclass":"good","ecoscore":88.48721806360732,"pageweight":561643,"requests":16,"speedindex":"G","speedindexclass":"verybad","speedscore":0.43},"url":"audits/contributions-indirectes-en-ligne/lighthouse/2021-03-11.json"}},"urls":{"api":"audits/contributions-indirectes-en-ligne/performance.json"}},"recommendation":{"scores":{"0":{"indexes":{"checked":2,"critical":2,"date":"2021-04-26","important":2,"medium":3,"pathlen":2,"total":27,"type":{"code":5,"structure":2,"text":0,"visual":0}},"url":"audits/contributions-indirectes-en-ligne/quality/2021-04-26.yml"},"1":{"indexes":{"checked":14,"critical":2,"date":"2022-04-05","important":5,"medium":7,"pathlen":2,"total":37,"type":{"code":0,"structure":0,"text":0,"visual":0}},"url":"audits/contributions-indirectes-en-ligne/quality/2022-04-05.yml"}},"urls":{"api":"audits/contributions-indirectes-en-ligne/recommendation.json"}}},"slug":"contributions-indirectes-en-ligne","title":"Contributions Indirectes En Ligne (CIEL)"},"declaration-douane-fret":{"audits":{"accessibility":{"rgaa":[{"context":{"audit":{"environment":["MacOS","Chrome","VoiceOver"],"guidelines":"RGAA 4.1","technologies":["HTML","CSS"],"tools":["Wave","AXE","MOZ DevTools","Usability Hike"]},"contacts":{"address":"11, rue des deux Communes, 93558 Montreuil, cedex FRANCE","email":"referent-accessibilite@douane.finances.gouv.fr"},"declared":{"audit":{"environment":["MacOS","Chrome","VoiceOver"],"guidelines":"RGAA 4.1","technologies":["HTML","CSS"],"tools":["Wave","AXE","MOZ DevTools","Usability Hike"]}},"path":"/audits/declaration-douane-fret/index.md","website":null},"date":"2021-07-21","score":{"compliance":45,"complianceaverage":50,"criteria":{"conforme":23,"nonapplicable":55,"nonconforme":28,"nonteste":0,"total":106}},"url":"audits/declaration-douane-fret/accessibility/2021-07-21.csv"}],"urls":{"api":"audits/declaration-douane-fret/accessibility.json","declaration":"audits/declaration-douane-fret/declaration.txt"}},"performance":{"scores":{"0":{"indexes":{"LCP":5274,"co2":1.493982487353324,"domsize":155,"eau":2.240973731029986,"ecoindex":"B","ecoindexclass":"good","ecoscore":75.3008756323338,"pageweight":1204558,"requests":54,"speedindex":"G","speedindexclass":"verybad","speedscore":0.32},"url":"audits/declaration-douane-fret/lighthouse/2021-03-10.json"}},"urls":{"api":"audits/declaration-douane-fret/performance.json"}}},"slug":"declaration-douane-fret","title":"Déclaration en douane – Fret traditionnel (DELTA G)"},"declaration-echanges-de-biens":{"audits":{"accessibility":{"rgaa":[{"context":{"audit":{"environment":["MacOS","Chrome","VoiceOver"],"guidelines":"RGAA 4.1","technologies":["HTML","CSS"],"tools":["Wave","AXE","MOZ DevTools","Usability Hike"]},"contacts":{"address":"11, rue des deux Communes, 93558 Montreuil, cedex FRANCE","email":"referent-accessibilite@douane.finances.gouv.fr"},"declared":{"audit":{"environment":["MacOS","Chrome","VoiceOver"],"guidelines":"RGAA 4.1","technologies":["HTML","CSS"],"tools":["Wave","AXE","MOZ DevTools","Usability Hike"]}},"path":"/audits/declaration-echanges-de-biens/index.md","website":null},"date":"2021-03-15","score":{"compliance":42,"complianceaverage":42,"criteria":{"conforme":12,"nonapplicable":78,"nonconforme":16,"nonteste":0,"total":106}},"url":"audits/declaration-echanges-de-biens/accessibility/2021-03-15.csv"}],"urls":{"api":"audits/declaration-echanges-de-biens/accessibility.json","declaration":"audits/declaration-echanges-de-biens/declaration.txt"}}},"slug":"declaration-echanges-de-biens","title":"Déclaration d'Échanges de Biens (DEB)"},"declaration-europeenne-service":{"audits":{"accessibility":{"rgaa":[{"context":{"audit":{"environment":["MacOS","Chrome","VoiceOver"],"guidelines":"RGAA 4.1","technologies":["HTML","CSS"],"tools":["Wave","AXE","MOZ DevTools","Usability Hike"]},"contacts":{"address":"11, rue des deux Communes, 93558 Montreuil, cedex FRANCE","email":"referent-accessibilite@douane.finances.gouv.fr"},"declared":{"audit":{"environment":["MacOS","Chrome","VoiceOver"],"guidelines":"RGAA 4.1","technologies":["HTML","CSS"],"tools":["Wave","AXE","MOZ DevTools","Usability Hike"]}},"path":"/audits/declaration-europeenne-service/index.md","website":null},"date":"2021-03-15","score":{"compliance":42,"complianceaverage":42,"criteria":{"conforme":12,"nonapplicable":78,"nonconforme":16,"nonteste":0,"total":106}},"url":"audits/declaration-europeenne-service/accessibility/2021-03-15.csv"}],"urls":{"api":"audits/declaration-europeenne-service/accessibility.json","declaration":"audits/declaration-europeenne-service/declaration.txt"}}},"slug":"declaration-europeenne-service","title":"Déclaration européenne de services (DES)"},"declaration-transit":{"audits":{"accessibility":{"rgaa":[{"context":{"audit":{"environment":["MacOS","Chrome","Voice Over"],"guidelines":"RGAA 4.1","technologies":["HTML","CSS"],"tools":["Wave","AXE","MOZ DevTools","Usability Hike"]},"contacts":{"address":"11, rue des deux Communes, 93558 Montreuil, cedex FRANCE","email":"referent-accessibilite@douane.finances.gouv.fr"},"declared":{"audit":{"environment":["MacOS","Chrome","Voice Over"],"guidelines":"RGAA 4.1","technologies":["HTML","CSS"],"tools":["Wave","AXE","MOZ DevTools","Usability Hike"]}},"path":"/audits/declaration-transit/index.md","website":null},"date":"2021-03-15","score":{"compliance":40,"complianceaverage":43,"criteria":{"conforme":28,"nonapplicable":35,"nonconforme":42,"nonteste":0,"total":105}},"url":"audits/declaration-transit/accessibility/2021-03-15.csv"}],"urls":{"api":"audits/declaration-transit/accessibility.json","declaration":"audits/declaration-transit/declaration.txt"}},"performance":{"scores":{"0":{"indexes":{"LCP":8311,"co2":2.092076675220733,"domsize":1423,"eau":3.1381150128310997,"ecoindex":"D","ecoindexclass":"bad","ecoscore":45.396166238963346,"pageweight":2659703,"requests":69,"speedindex":"G","speedindexclass":"verybad","speedscore":0.39},"url":"audits/declaration-transit/lighthouse/2021-03-10.json"}},"urls":{"api":"audits/declaration-transit/performance.json"}}},"slug":"declaration-transit","title":"Déclaration de transit communautaire (NSTI - Delta T)"},"gestion-mouvements-marchandises":{"audits":{"accessibility":{"rgaa":[{"context":{"audit":{"environment":["MacOS","Chrome","VoiceOver"],"guidelines":"RGAA 4.1","technologies":["HTML","CSS"],"tools":["Wave","AXE","MOZ DevTools","Usability Hike"]},"contacts":{"address":"11, rue des deux Communes, 93558 Montreuil, cedex FRANCE","email":"referent-accessibilite@douane.finances.gouv.fr"},"declared":{"audit":{"environment":["MacOS","Chrome","VoiceOver"],"guidelines":"RGAA 4.1","technologies":["HTML","CSS"],"tools":["Wave","AXE","MOZ DevTools","Usability Hike"]}},"path":"/audits/gestion-mouvements-marchandises/index.md","website":null},"date":"2021-10-26","score":{"compliance":36,"complianceaverage":46,"criteria":{"conforme":17,"nonapplicable":59,"nonconforme":30,"nonteste":0,"total":106}},"url":"audits/gestion-mouvements-marchandises/accessibility/2021-10-26.csv"},{"context":null,"date":"2021-03-15","score":{"compliance":26,"complianceaverage":51,"criteria":{"conforme":5,"nonapplicable":6,"nonconforme":14,"nonteste":0,"total":25}},"url":"audits/gestion-mouvements-marchandises/accessibility/2021-03-15.csv"}],"urls":{"api":"audits/gestion-mouvements-marchandises/accessibility.json","declaration":"audits/gestion-mouvements-marchandises/declaration.txt"}}},"slug":"gestion-mouvements-marchandises","title":"Gestion de l’Accompagnement des Mouvements de Marchandises soumises à Accises (EMCS-GAMMA)"},"portail-douane":{"audits":{"accessibility":{"rgaa":[{"context":{"audit":{"environment":["MacOS","Chrome","VoiceOver"],"guidelines":"RGAA 4.1","technologies":["HTML","CSS"],"tools":["Wave","AXE","MOZ DevTools","Usability Hike"]},"contacts":{"address":"11, rue des deux Communes, 93558 Montreuil, cedex FRANCE","email":"referent-accessibilite@douane.finances.gouv.fr"},"declared":{"audit":{"environment":["MacOS","Chrome","VoiceOver"],"guidelines":"RGAA 4.1","technologies":["HTML","CSS"],"tools":["Wave","AXE","MOZ DevTools","Usability Hike"]}},"path":"/audits/portail-douane/index.md","website":null},"date":"2021-09-07","score":{"compliance":54,"complianceaverage":80,"criteria":{"conforme":40,"nonapplicable":33,"nonconforme":33,"nonteste":0,"total":106}},"url":"audits/portail-douane/accessibility/2021-09-07.csv"},{"context":null,"date":"2021-03-19","score":{"compliance":75,"complianceaverage":82,"criteria":{"conforme":42,"nonapplicable":50,"nonconforme":14,"nonteste":0,"total":106}},"url":"audits/portail-douane/accessibility/2021-03-19.csv"}],"urls":{"api":"audits/portail-douane/accessibility.json","declaration":"audits/portail-douane/declaration.txt"}},"performance":{"scores":{"0":{"indexes":{"LCP":5743,"co2":4.038367126072998,"domsize":1498,"eau":6.0575506891094975,"ecoindex":"G","ecoindexclass":"bad","ecoscore":-51.918356303649915,"pageweight":7407218,"requests":70,"speedindex":"G","speedindexclass":"verybad","speedscore":0.26},"url":"audits/portail-douane/lighthouse/2021-05-11.json"}},"urls":{"api":"audits/portail-douane/performance.json"}},"recommendation":{"scores":{"0":{"indexes":{"checked":0,"critical":0,"date":"2021-04-26","important":0,"medium":0,"pathlen":2,"total":13,"type":{"code":0,"structure":0,"text":0,"visual":0}},"url":"audits/portail-douane/quality/2021-04-26.yml"}},"urls":{"api":"audits/portail-douane/recommendation.json"}}},"slug":"portail-douane","title":"Le portail de la direction générale des douanes et droits indirects"},"procedure-communautaire":{"audits":{"accessibility":{"rgaa":[{"context":{"audit":{"environment":["MacOS","Chrome","VoiceOver"],"guidelines":"RGAA 4.1","technologies":["HTML","CSS"],"tools":["Wave","AXE","MOZ DevTools","Usability Hike"]},"contacts":{"address":"11, rue des deux Communes, 93558 Montreuil, cedex FRANCE","email":"referent-accessibilite@douane.finances.gouv.fr"},"declared":{"audit":{"environment":["MacOS","Chrome","VoiceOver"],"guidelines":"RGAA 4.1","technologies":["HTML","CSS"],"tools":["Wave","AXE","MOZ DevTools","Usability Hike"]}},"path":"/audits/procedure-communautaire/index.md","website":null},"date":"2021-03-15","score":{"compliance":36,"complianceaverage":37,"criteria":{"conforme":15,"nonapplicable":64,"nonconforme":26,"nonteste":0,"total":105}},"url":"audits/procedure-communautaire/accessibility/2021-03-15.csv"}],"urls":{"api":"audits/procedure-communautaire/accessibility.json","declaration":"audits/procedure-communautaire/declaration.txt"}}},"slug":"procedure-communautaire","title":"Système de contrôle des exportations (ECS)"}}}